[
  {
    "id": 2,
    "nama": "AKUN FREEFIRE MAX 8 S6",
    "harga": "3.000.000.00",
    "deskripsi": "EP S6 DST\nMAX 8\nVAULT OTW 900\nall aman",
    "foto": "https://files.catbox.moe/l6cte6.jpg",
    "status": "ready"
  },
  {
    "id": 6,
    "nama": "AKUN FREE FIRE",
    "harga": "2.200.000.00",
    "deskripsi": "OTW MAX 8, SG LUMUT X REAPER\nEP DAN BOOYAH PAS RAPI",
    "foto": "https://files.catbox.moe/lxtuzp.jpg",
    "status": "ready"
  },
  {
    "id": 8,
    "nama": "AKUN FREE FIRE",
    "harga": "320.000.00",
    "deskripsi": "CN ON, TINJU ON, MB ON",
    "foto": "https://files.catbox.moe/cd27r4.jpg",
    "status": "ready"
  },
  {
    "id": 9,
    "nama": "AKUN FREE FIRE",
    "harga": "500.000.00",
    "deskripsi": "SET CEPCIL ON, GENJI ON, VAULT BANYAK",
    "foto": "https://files.catbox.moe/azhjpu.jpg",
    "status": "ready"
  },
  {
    "id": 12,
    "nama": "AKUN FREE FIRE",
    "harga": "550.000.00",
    "deskripsi": "EP S8, CLUBER ON, REGANAROK ON, EVO 2 MAX 1",
    "foto": "https://img.sanishtech.com/u/60fd9c189c3e8d89805276f864484eb2.jpg",
    "status": "ready"
  },
  {
    "id": 13,
    "nama": "AKUN FREE FIRE",
    "harga": "2.300.000.00",
    "deskripsi": "PRIME 8, MAX 9 OTW 10",
    "foto": "https://img.sanishtech.com/u/92d99fb6fb08550373dfa19abf8bc0e7.jpg",
    "status": "ready"
  },
  {
    "id": 14,
    "nama": "AKUN FREE FIRE",
    "harga": "280.000.00",
    "deskripsi": "ALL NARUTO PART 2 ON, EVO 4 MAX 1",
    "foto": "https://files.catbox.moe/cqjypx.jpg",
    "status": "ready"
  }
]